MANIFEST.in
README.md
setup.py
preprocessor/__init__.py
preprocessor.egg-info/PKG-INFO
preprocessor.egg-info/SOURCES.txt
preprocessor.egg-info/dependency_links.txt
preprocessor.egg-info/not-zip-safe
preprocessor.egg-info/top_level.txt
scripts/preprocessor