Metadata-Version: 1.1
Name: preprocessor
Version: 1.0.6
Summary: Preprocessor for files.
Home-page: https://github.com/nivwusquorum/preprocessor
Author: Szymon Sidor
Author-email: szymon.sidor@gmail.com
License: MIT
Download-URL: https://github.com/nivwusquorum/preprocessor
Keywords: Macros,Processing,FileIO
Platform: any
Classifier: Operating System :: OS Independent
Classifier: Programming Language :: Python :: 3.3
